lab4/Stoplight.v
//==============================================================================
// Stoplight Module for Lab 4
//
// Note on lights:
// 	Each bit represents the on/off signal for a light.
// 	Bit | Light
// 	------------
// 	0   | Red
// 	1   | Yellow
// 	2   | Green
//==============================================================================

module Stoplight(
	input            clk,         // Clock signal
	input            rst,         // Reset signal for FSM
	input            car_present, // Is there a car on Prospect?
	output reg [2:0] light_pros,  // Prospect Avenue Light
	output reg [2:0] light_wash   // Washington Road Light
);

	// Declare Local Vars Here
	reg [3:0] state;
	reg [3:0] next_state;
	// ...

	// Declare State Names 
	localparam STATE_ZERO  = 4'b0000;
	localparam STATE_ONE   = 4'b0001;
	localparam STATE_TWO   = 4'b0010;
	localparam STATE_THREE = 4'b0011;
	localparam STATE_FOUR  = 4'b0100;
	localparam STATE_FIVE  = 4'b0101;
	localparam STATE_SIX   = 4'b0110;
	localparam STATE_SEVEN = 4'b0111;
	localparam STATE_EIGHT = 4'b1000;
	localparam STATE_NINE  = 4'b1001;

	// Light Colors
	localparam RED = 3'b001;
	localparam YLW = 3'b010;
	localparam GRN = 3'b100;

	// Output Combinational Logic
	always @( * ) begin
		light_pros = GRN;
		light_wash = RED;

		if(state==STATE_NINE) begin light_pros = YLW; end	
		if(state <STATE_FIVE) begin light_pros = RED; end
		
		if(state==STATE_FOUR) begin light_wash = YLW; end
		if(state <STATE_FOUR) begin light_wash = GRN; end

	end

	// Next State Combinational Logic
	always @( * ) begin
		// Write your Next State Logic Here
		if (!car_present && state == STATE_THREE) begin next_state = STATE_THREE; end
		else if (state == STATE_NINE) begin next_state = STATE_ZERO; end
		else begin next_state = state + 1; end
	end

	// State Update Sequential Logic
	always @(posedge clk) begin
		if (rst) begin
			// Update state to reset state
			state <= STATE_ZERO;
		end
		else begin
			// Update state to next state
			state <= next_state;
		end
	end

endmodule

lab4/Stoplight.t.v
//==============================================================================
// Stoplight Testbench Module for Lab 4
//==============================================================================
`timescale 1ns/100ps

`include "Stoplight.v"

`define ASSERT_EQ(ONE, TWO, MSG)               \
	begin                                      \
		if ((ONE) !== (TWO)) begin             \
			$display("\t[FAILURE]:%s", (MSG)); \
			errors = errors + 1;               \
		end                                    \
	end #0

module StoplightTest;

	// Local Vars
	reg clk = 1;
	reg rst = 0;
	reg car = 0;
	reg [4:0] errors = 0;
	wire [2:0] lp, lw;

	// Light Colors
	localparam GRN = 3'b100;
	localparam YLW = 3'b010;
	localparam RED = 3'b001;

	// VCD Dump
	initial begin
		$dumpfile("StoplightTest.vcd");
		$dumpvars;
	end

	// Stoplight Module
	Stoplight light(
		.clk        (clk),
		.rst        (rst),
		.car_present(car),
		.light_pros (lp),
		.light_wash (lw)
	);

	// Clock
	always begin
		#2.5 clk = ~clk;
	end

	// Main Test Logic
	initial begin

		#1; 									// t = 1
		rst = 1; 

		@(posedge clk); 						// t = 5

		#1; 									// t = 6
		rst = 0;

		#1;										// t = 7
		if (lw !== GRN || lp !== RED) begin
			$display("Error at time %t", $time);
			errors = errors + 1;
		end

		@(posedge clk); 						// t = 10

		@(posedge clk); 						// t = 15
		@(posedge clk); 						// t = 20
		@(posedge clk); 						// t = 25
		@(posedge clk); 						// t = 30
		@(posedge clk); 						// t = 35
		@(posedge clk); 						// t = 40

		#1;										// t = 41
		car = 1;

		#1;										// t = 42
		if (lw !== GRN || lp !== RED) begin
			$display("Error at time %t", $time);
			errors = errors + 1;
		end

		@(posedge clk);							// t = 45
		@(posedge clk);							// t = 50

		#1;										// t = 51
		car = 0;

		#1;										// t = 52
		if (lw !== RED || lp !== GRN) begin
			$display("Error at time %t", $time);
			errors = errors + 1;
		end

		@(posedge clk);							// t = 55
		@(posedge clk);							// t = 60
		@(posedge clk);							// t = 65

		#1;										// t = 66
		car = 1;

		#1;										// t = 67
		if (lw !== RED || lp !== GRN) begin
			$display("Error at time %t", $time);
			errors = errors + 1;
		end

		@(posedge clk);							// t = 70
		@(posedge clk);							// t = 75

		#1;										// t = 76
		car = 1;

		#1;										// t = 77
		if (lw !== GRN || lp !== RED) begin
			$display("Error at time %t", $time);
			errors = errors + 1;
		end

		@(posedge clk);							// t = 80
		@(posedge clk);							// t = 85
		
		#1;										// t = 86
		car = 0;

		#1;										// t = 87
		if (lw !== GRN || lp !== RED) begin
			$display("Error at time %t", $time);
			errors = errors + 1;
		end

		@(posedge clk);							// t = 90
		@(posedge clk);							// t = 95
		@(posedge clk);							// t = 100
		@(posedge clk);							// t = 105

		#1;										// t = 106
		car = 1;

		#1;										// t = 107
		if (lw !== GRN || lp !== RED) begin
			$display("Error at time %t", $time);
			errors = errors + 1;
		end

		@(posedge clk);							// t = 110
		@(posedge clk);							// t = 115

		#1;										// t = 116
		car = 0;

		#1;										// t = 117
		if (lw !== RED || lp !== GRN) begin
			$display("Error at time %t", $time);
			errors = errors + 1;
		end

		@(posedge clk);							// t = 120
		@(posedge clk);							// t = 125
		@(posedge clk);							// t = 130

		#1;										// t = 131
		car = 1;

		#1;										// t = 132
		if (lw !== RED || lp !== GRN) begin
			$display("Error at time %t", $time);
			errors = errors + 1;
		end

		@(posedge clk);							// t = 135

		#1;										// t = 136
		car = 0;

		#1;										// t = 137
		if (lw !== RED || lp !== YLW) begin
			$display("Error at time %t", $time);
			errors = errors + 1;
		end

		@(posedge clk);							// t = 140

		$finish;
	end

endmodule

lab4/StoplightTest.vcd
$date
	Wed Oct 27 21:27:03 2021
$end
$version
	Icarus Verilog
$end
$timescale
	100ps
$end
$scope module StoplightTest $end
$var wire 3 ! lw [2:0] $end
$var wire 3 " lp [2:0] $end
$var reg 1 # car $end
$var reg 1 $ clk $end
$var reg 5 % errors [4:0] $end
$var reg 1 & rst $end
$scope module light $end
$var wire 1 # car_present $end
$var wire 1 $ clk $end
$var wire 1 & rst $end
$var reg 3 ' light_pros [2:0] $end
$var reg 3 ( light_wash [2:0] $end
$var reg 4 ) next_state [3:0] $end
$var reg 4 * state [3:0] $end
$upscope $end
$upscope $end
$enddefinitions $end
#0
$dumpvars
bx *
bx )
bx (
bx '
0&
b0 %
1$
0#
bx "
bx !
$end
#10
1&
#25
0$
#50
b1 )
b100 !
b100 (
b1 "
b1 '
b0 *
1$
#60
0&
#75
0$
#100
b10 )
b100 !
b100 (
b1 "
b1 '
b1 *
1$
#125
0$
#150
b11 )
b100 !
b100 (
b1 "
b1 '
b10 *
1$
#175
0$
#200
b100 !
b100 (
b1 "
b1 '
b11 *
1$
#225
0$
#250
1$
#275
0$
#300
1$
#325
0$
#350
1$
#375
0$
#400
1$
#410
b100 )
1#
#425
0$
#450
b101 )
b10 !
b10 (
b1 "
b1 '
b100 *
1$
#475
0$
#500
b110 )
b1 !
b1 (
b100 "
b100 '
b101 *
1$
#510
0#
#525
0$
#550
b111 )
b110 *
1$
#575
0$
#600
b1000 )
b111 *
1$
#625
0$
#650
b1001 )
b1000 *
1$
#660
1#
#675
0$
#700
b0 )
b10 "
b10 '
b1001 *
1$
#725
0$
#750
b1 )
b100 !
b100 (
b1 "
b1 '
b0 *
1$
#775
0$
#800
b10 )
b100 !
b100 (
b1 "
b1 '
b1 *
1$
#825
0$
#850
b11 )
b100 !
b100 (
b1 "
b1 '
b10 *
1$
#860
0#
#875
0$
#900
b100 !
b100 (
b1 "
b1 '
b11 *
1$
#925
0$
#950
1$
#975
0$
#1000
1$
#1025
0$
#1050
1$
#1060
b100 )
1#
#1075
0$
#1100
b101 )
b10 !
b10 (
b1 "
b1 '
b100 *
1$
#1125
0$
#1150
b110 )
b1 !
b1 (
b100 "
b100 '
b101 *
1$
#1160
0#
#1175
0$
#1200
b111 )
b110 *
1$
#1225
0$
#1250
b1000 )
b111 *
1$
#1275
0$
#1300
b1001 )
b1000 *
1$
#1310
1#
#1325
0$
#1350
b0 )
b10 "
b10 '
b1001 *
1$
#1360
0#
#1375
0$
#1400
b1 )
b100 !
b100 (
b1 "
b1 '
b0 *
1$
